ibvpy/__init__.py
ibvpy/api.py
ibvpy/version.py
ibvpy/bcond/__init__.py
ibvpy/bcond/bc_dof.py
ibvpy/bcond/bc_dofgroup.py
ibvpy/bcond/bc_list.py
ibvpy/bcond/bc_slice.py
ibvpy/bcond/bc_slice_I.py
ibvpy/bcond/bcond_mngr.py
ibvpy/bcond/i_bcond.py
ibvpy/fets/__init__.py
ibvpy/fets/fets.py
ibvpy/fets/i_fets.py
ibvpy/fets/fets1D/__init__.py
ibvpy/fets/fets1D/fets1D2l.py
ibvpy/fets/fets1D/fets1D2l3u.py
ibvpy/fets/fets1D5/__init__.py
ibvpy/fets/fets1D5/fets1D5.py
ibvpy/fets/fets1D5/fets1d52ulrh.py
ibvpy/fets/fets2D/__init__.py
ibvpy/fets/fets2D/fets2D.py
ibvpy/fets/fets2D/fets2D4q.py
ibvpy/fets/fets2D/fets2D4q12u.py
ibvpy/fets/fets2D/fets2D4q16u.py
ibvpy/fets/fets2D/fets2D4q4t.py
ibvpy/fets/fets2D/fets2D4q8u.py
ibvpy/fets/fets2D/fets2D4q9u.py
ibvpy/fets/fets2D/fets2D9q.py
ibvpy/fets/fets2D/fets2Drotsym.py
ibvpy/fets/fets2D/fets2Dtf.py
ibvpy/fets/fets2D/vfets2D4q.py
ibvpy/fets/fets2D5/__init__.py
ibvpy/fets/fets2D5/__test__.py
ibvpy/fets/fets2D5/coordinate_transformations.py
ibvpy/fets/fets2D5/fets2D5.py
ibvpy/fets/fets2D5/fets2D58h.py
ibvpy/fets/fets2D5/fets2D58h16u.py
ibvpy/fets/fets2D5/fets2D58h20u.py
ibvpy/fets/fets2D5/fets2D58h24u.py
ibvpy/fets/fets2D5/fets2D58h32u.py
ibvpy/fets/fets3D/__init__.py
ibvpy/fets/fets3D/fets3D.py
ibvpy/fets/fets3D/fets3D8h.py
ibvpy/fets/fets3D/fets3D8h16u.py
ibvpy/fets/fets3D/fets3D8h20u.py
ibvpy/fets/fets3D/fets3D8h24u.py
ibvpy/fets/fets3D/fets3D8h27u.py
ibvpy/fets/fets3D/fets3D8h32u.py
ibvpy/fets/fets3D/vfets3D8h.py
ibvpy/mathkit/__init__.py
ibvpy/mathkit/array/__init__.py
ibvpy/mathkit/array/smoothing.py
ibvpy/mathkit/geo/__init__.py
ibvpy/mathkit/geo/geo_ndgrid.py
ibvpy/mathkit/geo/transform/__init__.py
ibvpy/mathkit/geo/transform/square2circle.py
ibvpy/mathkit/level_set/__init__.py
ibvpy/mathkit/level_set/level_set.py
ibvpy/mathkit/linalg/__init__.py
ibvpy/mathkit/linalg/__test__.py
ibvpy/mathkit/linalg/coo_mtx.py
ibvpy/mathkit/linalg/dense_mtx.py
ibvpy/mathkit/linalg/linalg_solver.py
ibvpy/mathkit/linalg/sys_matrix.py
bmcs_ibvpy-0.0.32a0.dist-info/METADATA
bmcs_ibvpy-0.0.32a0.dist-info/WHEEL
bmcs_ibvpy-0.0.32a0.dist-info/top_level.txt
bmcs_ibvpy-0.0.32a0.dist-info/RECORD
